ap/__init__.py
ap/__main__.py
ap/cli.py
ap/cli_commands/__init__.py
ap/cli_commands/display_tree.py
ap/cli_commands/explain.py
ap/cli_commands/generate_map.py
ap/cli_commands/generate_quiz.py
ap/cli_commands/init_config.py
ap/cli_commands/quiz.py
ap/cli_commands/study.py
ap/core/__init__.py
ap/core/concept_map.py
ap/core/concept_validator.py
ap/core/quiz_quality_checker.py
ap/core/settings.py
ap/core/utils.py
ap/tests/__init__.py
ap/tests/test_concept_map.py
ap_cli-1.18.1.dist-info/METADATA
ap_cli-1.18.1.dist-info/WHEEL
ap_cli-1.18.1.dist-info/entry_points.txt
ap_cli-1.18.1.dist-info/top_level.txt
ap_cli-1.18.1.dist-info/RECORD
