Metadata-Version: 2.4
Name: ap-cli
Version: 1.18.1
Summary: 一个帮助用户通过提问-生成-测验循环来学习新概念的命令行工具
Home-page: https://github.com/yangjh-xbmu/ap
Author: yangjh
Author-email: yangjh@xbmu.edu.cn
Classifier: Development Status :: 4 - Beta
Classifier: Intended Audience :: Education
Classifier: License :: OSI Approved :: MIT License
Classifier: Operating System :: OS Independent
Classifier: Programming Language :: Python :: 3
Classifier: Programming Language :: Python :: 3.8
Classifier: Programming Language :: Python :: 3.9
Classifier: Programming Language :: Python :: 3.10
Classifier: Programming Language :: Python :: 3.11
Classifier: Programming Language :: Python :: 3.12
Requires-Python: >=3.8
Requires-Dist: typer==0.19.2
Requires-Dist: openai>=1.109.0
Requires-Dist: python-dotenv==1.0.0
Requires-Dist: PyYAML==6.0.1
Requires-Dist: httpx[socks]
Dynamic: author
Dynamic: author-email
Dynamic: classifier
Dynamic: description
Dynamic: description-content-type
Dynamic: home-page
Dynamic: requires-dist
Dynamic: requires-python
Dynamic: summary
